cvbox/__init__.py
cvbox/fileio/__init__.py
cvbox/fileio/json_dict.py
cvbox/fileio/permissions.py
cvbox/fileio/pkl.py
cvbox/search/__init__.py
cvbox/search/list_files.py
cvbox-0.0.5.dist-info/LICENSE
cvbox-0.0.5.dist-info/METADATA
cvbox-0.0.5.dist-info/WHEEL
cvbox-0.0.5.dist-info/top_level.txt
cvbox-0.0.5.dist-info/RECORD
